octostar_streamlit_search_experience/__init__.py
octostar_streamlit_search_experience/frontend/.eslintrc.cjs
octostar_streamlit_search_experience/frontend/.gitignore
octostar_streamlit_search_experience/frontend/README.md
octostar_streamlit_search_experience/frontend/dist/assets/index-B12znyeL.css
octostar_streamlit_search_experience/frontend/dist/assets/index-v59EGv46.js
octostar_streamlit_search_experience/frontend/dist/index.html
octostar_streamlit_search_experience/frontend/index.html
octostar_streamlit_search_experience/frontend/package-lock.json
octostar_streamlit_search_experience/frontend/package.json
octostar_streamlit_search_experience/frontend/src/App.tsx
octostar_streamlit_search_experience/frontend/src/components/Dropzone/Dropzone.module.css
octostar_streamlit_search_experience/frontend/src/components/Dropzone/Dropzone.tsx
octostar_streamlit_search_experience/frontend/src/components/SearchExperienceButton/SearchExperienceButton.module.css
octostar_streamlit_search_experience/frontend/src/components/SearchExperienceButton/SearchExperienceButton.tsx
octostar_streamlit_search_experience/frontend/src/main.tsx
octostar_streamlit_search_experience/frontend/src/types.ts
octostar_streamlit_search_experience/frontend/src/vite-env.d.ts
octostar_streamlit_search_experience/frontend/tsconfig.json
octostar_streamlit_search_experience/frontend/tsconfig.node.json
octostar_streamlit_search_experience/frontend/vite.config.ts
octostar_streamlit_search_experience-0.1.5.dist-info/METADATA
octostar_streamlit_search_experience-0.1.5.dist-info/WHEEL
octostar_streamlit_search_experience-0.1.5.dist-info/RECORD
