Metadata-Version: 2.1
Name: octostar-streamlit-search-experience
Version: 0.1.5
Summary: 
License: MIT
Author: Your Name
Author-email: you@example.com
Requires-Python: >=3.9, !=2.7.*, !=3.0.*, !=3.1.*, !=3.2.*, !=3.3.*, !=3.4.*, !=3.5.*, !=3.6.*, !=3.7.*, !=3.8.*
Classifier: License :: OSI Approved :: MIT License
Classifier: Programming Language :: Python :: 3
Classifier: Programming Language :: Python :: 3.9
Classifier: Programming Language :: Python :: 3.10
Classifier: Programming Language :: Python :: 3.11
Classifier: Programming Language :: Python :: 3.12
Requires-Dist: pydantic (>=2.7.1,<3.0.0)
Requires-Dist: streamlit (>=1.34.0,<2.0.0)
Requires-Dist: streamlit-octostar-research (>=0.1.22,<0.2.0)
